{
  "updated_at": "08-06-2026 05:23",
  "source": "https://sliedrechtdoet.nl/agenda",
  "count": 12,
  "activities": [
    {
      "title": "Ontmoet elkaar in de groene huiskamer",
      "desc": "Ontmoet elkaar in de groene huiskamer",
      "url": "https://sliedrechtdoet.nl/agenda/143274/2026-06-08/ontmoet-elkaar-in-de-groene-huiskamer-2",
      "location": "",
      "scores": {
        "snelwandelaar": 0,
        "etalagekijker": 0,
        "buurtprater": 0,
        "handen": 0,
        "hersens": 0,
        "bakkie": 0,
        "ochtend": 0,
        "middag": 0,
        "avond": 0
      },
      "raw_text": "Ontmoet elkaar in de groene huiskamer"
    },
    {
      "title": "Leer Nederlands in de moestuin",
      "desc": "Leer Nederlands in de moestuin",
      "url": "https://sliedrechtdoet.nl/agenda/143269/2026-06-08/leer-nederlands-in-de-moestuin",
      "location": "",
      "scores": {
        "snelwandelaar": 0,
        "etalagekijker": 0,
        "buurtprater": 0,
        "handen": 3,
        "hersens": 1,
        "bakkie": 0,
        "ochtend": 0,
        "middag": 0,
        "avond": 0
      },
      "raw_text": "Leer Nederlands in de moestuin"
    },
    {
      "title": "Lunchen op de Moestuin",
      "desc": "Lunchen op de Moestuin",
      "url": "https://sliedrechtdoet.nl/agenda/143267/2026-06-08/lunchen-op-de-moestuin",
      "location": "",
      "scores": {
        "snelwandelaar": 0,
        "etalagekijker": 1,
        "buurtprater": 3,
        "handen": 3,
        "hersens": 1,
        "bakkie": 3,
        "ochtend": 0,
        "middag": 3,
        "avond": 0
      },
      "raw_text": "Lunchen op de Moestuin"
    },
    {
      "title": "Ontdek Sliedrecht in het onderhuis",
      "desc": "Ontdek Sliedrecht in het onderhuis",
      "url": "https://sliedrechtdoet.nl/agenda/138904/2026-06-08/ontdek-sliedrecht-in-het-onderhuis",
      "location": "",
      "scores": {
        "snelwandelaar": 0,
        "etalagekijker": 0,
        "buurtprater": 0,
        "handen": 0,
        "hersens": 0,
        "bakkie": 0,
        "ochtend": 0,
        "middag": 0,
        "avond": 0
      },
      "raw_text": "Ontdek Sliedrecht in het onderhuis"
    },
    {
      "title": "Samen gezellig wandelen door Sliedrecht",
      "desc": "Samen gezellig wandelen door Sliedrecht",
      "url": "https://sliedrechtdoet.nl/agenda/138335/2026-06-08/samen-gezellig-wandelen-door-sliedrecht",
      "location": "",
      "scores": {
        "snelwandelaar": 3,
        "etalagekijker": 1,
        "buurtprater": 3,
        "handen": 3,
        "hersens": 1,
        "bakkie": 3,
        "ochtend": 0,
        "middag": 0,
        "avond": 0
      },
      "raw_text": "Samen gezellig wandelen door Sliedrecht"
    },
    {
      "title": "Huiswerkbegeleiding",
      "desc": "Huiswerkbegeleiding",
      "url": "https://sliedrechtdoet.nl/agenda/129396/2026-06-08/huiswerkbegeleiding-6",
      "location": "",
      "scores": {
        "snelwandelaar": 0,
        "etalagekijker": 0,
        "buurtprater": 0,
        "handen": 0,
        "hersens": 0,
        "bakkie": 0,
        "ochtend": 0,
        "middag": 0,
        "avond": 0
      },
      "raw_text": "Huiswerkbegeleiding"
    },
    {
      "title": "Ontmoet andere ouders",
      "desc": "Ontmoet andere ouders",
      "url": "https://sliedrechtdoet.nl/agenda/136644/2026-06-09/ontmoet-andere-ouders-2",
      "location": "",
      "scores": {
        "snelwandelaar": 0,
        "etalagekijker": 0,
        "buurtprater": 0,
        "handen": 0,
        "hersens": 0,
        "bakkie": 0,
        "ochtend": 0,
        "middag": 0,
        "avond": 0
      },
      "raw_text": "Ontmoet andere ouders"
    },
    {
      "title": "Laat je inspireren tijdens koffie met...",
      "desc": "Laat je inspireren tijdens koffie met...",
      "url": "https://sliedrechtdoet.nl/agenda/118472/2026-06-09/laat-je-inspireren-tijdens-koffie-met",
      "location": "",
      "scores": {
        "snelwandelaar": 0,
        "etalagekijker": 1,
        "buurtprater": 3,
        "handen": 0,
        "hersens": 1,
        "bakkie": 3,
        "ochtend": 0,
        "middag": 0,
        "avond": 0
      },
      "raw_text": "Laat je inspireren tijdens koffie met..."
    },
    {
      "title": "Geniet van een heerlijke lunch voor €2,50",
      "desc": "Geniet van een heerlijke lunch voor €2,50",
      "url": "https://sliedrechtdoet.nl/agenda/136861/2026-06-09/geniet-van-een-heerlijke-lunch-voor-2-50",
      "location": "",
      "scores": {
        "snelwandelaar": 0,
        "etalagekijker": 1,
        "buurtprater": 3,
        "handen": 0,
        "hersens": 1,
        "bakkie": 3,
        "ochtend": 0,
        "middag": 3,
        "avond": 0
      },
      "raw_text": "Geniet van een heerlijke lunch voor €2,50"
    },
    {
      "title": "Aangehaakt",
      "desc": "Aangehaakt",
      "url": "https://sliedrechtdoet.nl/agenda/129383/2026-06-09/aangehaakt",
      "location": "",
      "scores": {
        "snelwandelaar": 0,
        "etalagekijker": 0,
        "buurtprater": 0,
        "handen": 0,
        "hersens": 0,
        "bakkie": 0,
        "ochtend": 0,
        "middag": 0,
        "avond": 0
      },
      "raw_text": "Aangehaakt"
    },
    {
      "title": "Voorlezen en kleuren in het thema van het boek!",
      "desc": "Voorlezen en kleuren in het thema van het boek!",
      "url": "https://sliedrechtdoet.nl/agenda/133610/2026-06-09/voorlezen-en-kleuren-in-het-thema-van-het-boek",
      "location": "",
      "scores": {
        "snelwandelaar": 0,
        "etalagekijker": 3,
        "buurtprater": 1,
        "handen": 0,
        "hersens": 0,
        "bakkie": 0,
        "ochtend": 0,
        "middag": 0,
        "avond": 0
      },
      "raw_text": "Voorlezen en kleuren in het thema van het boek!"
    },
    {
      "title": "Sliedrecht Doet ontmoet je op de weekmarkt!",
      "desc": "Sliedrecht Doet ontmoet je op de weekmarkt!",
      "url": "https://sliedrechtdoet.nl/agenda/144355/2026-06-10/sliedrecht-doet-ontmoet-je-op-de-weekmarkt",
      "location": "",
      "scores": {
        "snelwandelaar": 0,
        "etalagekijker": 0,
        "buurtprater": 0,
        "handen": 0,
        "hersens": 0,
        "bakkie": 0,
        "ochtend": 0,
        "middag": 0,
        "avond": 0
      },
      "raw_text": "Sliedrecht Doet ontmoet je op de weekmarkt!"
    }
  ]
}